{
    "uid": "10d7187d-e655-4ec8-a805-922d33361e14",
    "name": "21_LightGBM",
    "preprocessing": [
        {
            "scale_y": {
                "scale": [
                    0.6799159643643367
                ],
                "mean": [
                    5.50112842359877
                ],
                "var": [
                    0.46228571859748596
                ],
                "n_samples_seen": 6953,
                "n_features_in": 1,
                "columns": [
                    "target"
                ],
                "scale_method": "scale_log_and_normal",
                "X_min_values": [
                    14.0
                ]
            },
            "ml_task": "regression",
            "params": {
                "columns_preprocessing": {},
                "target_preprocessing": [
                    "na_exclude",
                    "scale_log_and_normal"
                ],
                "ml_task": "regression"
            }
        },
        {
            "scale_y": {
                "scale": [
                    0.6833976813941459
                ],
                "mean": [
                    5.497954006130596
                ],
                "var": [
                    0.4670323909348946
                ],
                "n_samples_seen": 6953,
                "n_features_in": 1,
                "columns": [
                    "target"
                ],
                "scale_method": "scale_log_and_normal",
                "X_min_values": [
                    14.0
                ]
            },
            "ml_task": "regression",
            "params": {
                "columns_preprocessing": {},
                "target_preprocessing": [
                    "na_exclude",
                    "scale_log_and_normal"
                ],
                "ml_task": "regression"
            }
        },
        {
            "scale_y": {
                "scale": [
                    0.6808058646134162
                ],
                "mean": [
                    5.498187222124968
                ],
                "var": [
                    0.4634966252920211
                ],
                "n_samples_seen": 6954,
                "n_features_in": 1,
                "columns": [
                    "target"
                ],
                "scale_method": "scale_log_and_normal",
                "X_min_values": [
                    14.0
                ]
            },
            "ml_task": "regression",
            "params": {
                "columns_preprocessing": {},
                "target_preprocessing": [
                    "na_exclude",
                    "scale_log_and_normal"
                ],
                "ml_task": "regression"
            }
        },
        {
            "scale_y": {
                "scale": [
                    0.6781213827453423
                ],
                "mean": [
                    5.499997731973519
                ],
                "var": [
                    0.45984860973645497
                ],
                "n_samples_seen": 6954,
                "n_features_in": 1,
                "columns": [
                    "target"
                ],
                "scale_method": "scale_log_and_normal",
                "X_min_values": [
                    14.0
                ]
            },
            "ml_task": "regression",
            "params": {
                "columns_preprocessing": {},
                "target_preprocessing": [
                    "na_exclude",
                    "scale_log_and_normal"
                ],
                "ml_task": "regression"
            }
        },
        {
            "scale_y": {
                "scale": [
                    0.7659626695199554
                ],
                "mean": [
                    5.376335106128386
                ],
                "var": [
                    0.5866988110981365
                ],
                "n_samples_seen": 6954,
                "n_features_in": 1,
                "columns": [
                    "target"
                ],
                "scale_method": "scale_log_and_normal",
                "X_min_values": [
                    36.0
                ]
            },
            "ml_task": "regression",
            "params": {
                "columns_preprocessing": {},
                "target_preprocessing": [
                    "na_exclude",
                    "scale_log_and_normal"
                ],
                "ml_task": "regression"
            }
        }
    ],
    "learners": [
        {
            "library_version": "3.3.3",
            "algorithm_name": "LightGBM",
            "algorithm_short_name": "LightGBM",
            "uid": "d1e30d5c-9625-4ff1-8343-b94520308a6a",
            "params": {
                "model_type": "LightGBM",
                "ml_task": "regression",
                "n_jobs": -1,
                "seed": 1236,
                "objective": "regression",
                "num_leaves": 63,
                "learning_rate": 0.2,
                "feature_fraction": 0.5,
                "bagging_fraction": 1.0,
                "min_data_in_leaf": 10,
                "metric": "l1",
                "custom_eval_metric_name": null,
                "explain_level": 0
            },
            "name": "learner_fold_0"
        },
        {
            "library_version": "3.3.3",
            "algorithm_name": "LightGBM",
            "algorithm_short_name": "LightGBM",
            "uid": "52f05a8e-f331-4a98-9b96-06cb2b7ccc5c",
            "params": {
                "model_type": "LightGBM",
                "ml_task": "regression",
                "n_jobs": -1,
                "seed": 1236,
                "objective": "regression",
                "num_leaves": 63,
                "learning_rate": 0.2,
                "feature_fraction": 0.5,
                "bagging_fraction": 1.0,
                "min_data_in_leaf": 10,
                "metric": "l1",
                "custom_eval_metric_name": null,
                "explain_level": 0
            },
            "name": "learner_fold_1"
        },
        {
            "library_version": "3.3.3",
            "algorithm_name": "LightGBM",
            "algorithm_short_name": "LightGBM",
            "uid": "e17e7bbb-4c28-4410-a8b3-33daa009fcf1",
            "params": {
                "model_type": "LightGBM",
                "ml_task": "regression",
                "n_jobs": -1,
                "seed": 1236,
                "objective": "regression",
                "num_leaves": 63,
                "learning_rate": 0.2,
                "feature_fraction": 0.5,
                "bagging_fraction": 1.0,
                "min_data_in_leaf": 10,
                "metric": "l1",
                "custom_eval_metric_name": null,
                "explain_level": 0
            },
            "name": "learner_fold_2"
        },
        {
            "library_version": "3.3.3",
            "algorithm_name": "LightGBM",
            "algorithm_short_name": "LightGBM",
            "uid": "c4f68856-edc2-43e5-86e3-3709f6665c8a",
            "params": {
                "model_type": "LightGBM",
                "ml_task": "regression",
                "n_jobs": -1,
                "seed": 1236,
                "objective": "regression",
                "num_leaves": 63,
                "learning_rate": 0.2,
                "feature_fraction": 0.5,
                "bagging_fraction": 1.0,
                "min_data_in_leaf": 10,
                "metric": "l1",
                "custom_eval_metric_name": null,
                "explain_level": 0
            },
            "name": "learner_fold_3"
        },
        {
            "library_version": "3.3.3",
            "algorithm_name": "LightGBM",
            "algorithm_short_name": "LightGBM",
            "uid": "587f4412-4962-4bf6-862f-11e17c6ee692",
            "params": {
                "model_type": "LightGBM",
                "ml_task": "regression",
                "n_jobs": -1,
                "seed": 1236,
                "objective": "regression",
                "num_leaves": 63,
                "learning_rate": 0.2,
                "feature_fraction": 0.5,
                "bagging_fraction": 1.0,
                "min_data_in_leaf": 10,
                "metric": "l1",
                "custom_eval_metric_name": null,
                "explain_level": 0
            },
            "name": "learner_fold_4"
        }
    ],
    "params": {
        "additional": {
            "max_rounds": 10000,
            "early_stopping_rounds": 50,
            "max_rows_limit": null,
            "max_cols_limit": null
        },
        "preprocessing": {
            "columns_preprocessing": {},
            "target_preprocessing": [
                "na_exclude",
                "scale_log_and_normal"
            ],
            "ml_task": "regression"
        },
        "validation_strategy": {
            "validation_type": "kfold",
            "k_folds": 5,
            "shuffle": true,
            "X_path": "AutoML_1\\X.data",
            "y_path": "AutoML_1\\y.data",
            "results_path": "AutoML_1"
        },
        "learner": {
            "model_type": "LightGBM",
            "ml_task": "regression",
            "n_jobs": -1,
            "seed": 1236,
            "objective": "regression",
            "num_leaves": 63,
            "learning_rate": 0.2,
            "feature_fraction": 0.5,
            "bagging_fraction": 1.0,
            "min_data_in_leaf": 10,
            "metric": "l1",
            "custom_eval_metric_name": null,
            "explain_level": 0
        },
        "automl_random_state": 1234,
        "ml_task": "regression",
        "explain_level": 0,
        "name": "21_LightGBM",
        "status": "initialized",
        "final_loss": null,
        "train_time": null,
        "data_type": "original",
        "max_time_for_learner": 72.0
    },
    "saved": [
        "21_LightGBM\\learner_fold_0.lightgbm",
        "21_LightGBM\\learner_fold_1.lightgbm",
        "21_LightGBM\\learner_fold_2.lightgbm",
        "21_LightGBM\\learner_fold_3.lightgbm",
        "21_LightGBM\\learner_fold_4.lightgbm"
    ],
    "predictions_fname": "21_LightGBM\\predictions_out_of_folds.csv",
    "metric_name": "mae",
    "final_loss": 57.143751521251176,
    "train_time": 7.3996076583862305,
    "is_stacked": false
}